{"v":4,"entries":{"components-dropdown--docs":{"id":"components-dropdown--docs","title":"Components/Dropdown","name":"Docs","importPath":"./src/components/default/dropdown/Dropdown.stories.tsx","type":"docs","tags":["autodocs","docs"],"storiesImports":[]},"components-dropdown--default":{"type":"story","id":"components-dropdown--default","name":"Default","title":"Components/Dropdown","importPath":"./src/components/default/dropdown/Dropdown.stories.tsx","tags":["autodocs","story"]},"components-input--docs":{"id":"components-input--docs","title":"Components/Input","name":"Docs","importPath":"./src/components/default/input/Input.stories.tsx","type":"docs","tags":["autodocs","docs"],"storiesImports":[]},"components-input--default":{"type":"story","id":"components-input--default","name":"Default","title":"Components/Input","importPath":"./src/components/default/input/Input.stories.tsx","tags":["autodocs","story"]},"components-input--with-value":{"type":"story","id":"components-input--with-value","name":"With Value","title":"Components/Input","importPath":"./src/components/default/input/Input.stories.tsx","tags":["autodocs","story"]},"components-input--with-error":{"type":"story","id":"components-input--with-error","name":"With Error","title":"Components/Input","importPath":"./src/components/default/input/Input.stories.tsx","tags":["autodocs","story"]},"components-cardpreview--docs":{"id":"components-cardpreview--docs","title":"Components/CardPreview","name":"Docs","importPath":"./src/components/newCardPage/cardPreview/CardPreview.stories.tsx","type":"docs","tags":["autodocs","docs"],"storiesImports":[]},"components-cardpreview--default":{"type":"story","id":"components-cardpreview--default","name":"Default","title":"Components/CardPreview","importPath":"./src/components/newCardPage/cardPreview/CardPreview.stories.tsx","tags":["autodocs","story"]},"components-cardpreview--master-card":{"type":"story","id":"components-cardpreview--master-card","name":"Master Card","title":"Components/CardPreview","importPath":"./src/components/newCardPage/cardPreview/CardPreview.stories.tsx","tags":["autodocs","story"]},"components-cardpreview--visa":{"type":"story","id":"components-cardpreview--visa","name":"Visa","title":"Components/CardPreview","importPath":"./src/components/newCardPage/cardPreview/CardPreview.stories.tsx","tags":["autodocs","story"]},"components-cardpreview--bc카드":{"type":"story","id":"components-cardpreview--bc카드","name":"BC카드","title":"Components/CardPreview","importPath":"./src/components/newCardPage/cardPreview/CardPreview.stories.tsx","tags":["autodocs","story"]},"components-cardpreview--신한카드":{"type":"story","id":"components-cardpreview--신한카드","name":"신한카드","title":"Components/CardPreview","importPath":"./src/components/newCardPage/cardPreview/CardPreview.stories.tsx","tags":["autodocs","story"]},"components-cardpreview--카카오뱅크":{"type":"story","id":"components-cardpreview--카카오뱅크","name":"카카오뱅크","title":"Components/CardPreview","importPath":"./src/components/newCardPage/cardPreview/CardPreview.stories.tsx","tags":["autodocs","story"]},"components-cardpreview--현대카드":{"type":"story","id":"components-cardpreview--현대카드","name":"현대카드","title":"Components/CardPreview","importPath":"./src/components/newCardPage/cardPreview/CardPreview.stories.tsx","tags":["autodocs","story"]},"components-cardpreview--우리카드":{"type":"story","id":"components-cardpreview--우리카드","name":"우리카드","title":"Components/CardPreview","importPath":"./src/components/newCardPage/cardPreview/CardPreview.stories.tsx","tags":["autodocs","story"]},"components-cardpreview--롯데카드":{"type":"story","id":"components-cardpreview--롯데카드","name":"롯데카드","title":"Components/CardPreview","importPath":"./src/components/newCardPage/cardPreview/CardPreview.stories.tsx","tags":["autodocs","story"]},"components-cardpreview--하나카드":{"type":"story","id":"components-cardpreview--하나카드","name":"하나카드","title":"Components/CardPreview","importPath":"./src/components/newCardPage/cardPreview/CardPreview.stories.tsx","tags":["autodocs","story"]},"components-cardpreview--국민카드":{"type":"story","id":"components-cardpreview--국민카드","name":"국민카드","title":"Components/CardPreview","importPath":"./src/components/newCardPage/cardPreview/CardPreview.stories.tsx","tags":["autodocs","story"]},"components-cardpreview--back-card":{"type":"story","id":"components-cardpreview--back-card","name":"Back Card","title":"Components/CardPreview","importPath":"./src/components/newCardPage/cardPreview/CardPreview.stories.tsx","tags":["autodocs","story"]},"components-newcardinputsection--docs":{"id":"components-newcardinputsection--docs","title":"Components/NewCardInputSection","name":"Docs","importPath":"./src/components/newCardPage/newCardInputSection/NewCardInputSection.stories.tsx","type":"docs","tags":["autodocs","docs"],"storiesImports":[]},"components-newcardinputsection--default":{"type":"story","id":"components-newcardinputsection--default","name":"Default","title":"Components/NewCardInputSection","importPath":"./src/components/newCardPage/newCardInputSection/NewCardInputSection.stories.tsx","tags":["autodocs","story"]},"components-newcardinputsection--password":{"type":"story","id":"components-newcardinputsection--password","name":"Password","title":"Components/NewCardInputSection","importPath":"./src/components/newCardPage/newCardInputSection/NewCardInputSection.stories.tsx","tags":["autodocs","story"]},"components-newcardinputsection--cvc":{"type":"story","id":"components-newcardinputsection--cvc","name":"CVC","title":"Components/NewCardInputSection","importPath":"./src/components/newCardPage/newCardInputSection/NewCardInputSection.stories.tsx","tags":["autodocs","story"]},"components-newcardinputsection--user-name":{"type":"story","id":"components-newcardinputsection--user-name","name":"User Name","title":"Components/NewCardInputSection","importPath":"./src/components/newCardPage/newCardInputSection/NewCardInputSection.stories.tsx","tags":["autodocs","story"]},"components-newcardinputsection--card-expiration":{"type":"story","id":"components-newcardinputsection--card-expiration","name":"Card Expiration","title":"Components/NewCardInputSection","importPath":"./src/components/newCardPage/newCardInputSection/NewCardInputSection.stories.tsx","tags":["autodocs","story"]},"components-newcardinputsection--card-company":{"type":"story","id":"components-newcardinputsection--card-company","name":"Card Company","title":"Components/NewCardInputSection","importPath":"./src/components/newCardPage/newCardInputSection/NewCardInputSection.stories.tsx","tags":["autodocs","story"]},"components-newcardinputsection--card-numbers":{"type":"story","id":"components-newcardinputsection--card-numbers","name":"Card Numbers","title":"Components/NewCardInputSection","importPath":"./src/components/newCardPage/newCardInputSection/NewCardInputSection.stories.tsx","tags":["autodocs","story"]}}}
